jobspy/__init__.py
jobspy/jobs/__init__.py
jobspy/scrapers/__init__.py
jobspy/scrapers/exceptions.py
jobspy/scrapers/glassdoor/__init__.py
jobspy/scrapers/indeed/__init__.py
jobspy/scrapers/linkedin/__init__.py
jobspy/scrapers/utils.py
jobspy/scrapers/ziprecruiter/__init__.py
python_jobspy_mini-1.1.53.dist-info/LICENSE
python_jobspy_mini-1.1.53.dist-info/METADATA
python_jobspy_mini-1.1.53.dist-info/WHEEL
python_jobspy_mini-1.1.53.dist-info/RECORD
