Metadata-Version: 2.1
Name: python-jobspy-mini
Version: 1.1.53
Summary: Job scraper for LinkedIn, Indeed, Glassdoor & ZipRecruiter
Home-page: https://github.com/Bunsly/JobSpy
Requires-Python: >=3.10,<4.0
Classifier: Programming Language :: Python :: 3
Classifier: Programming Language :: Python :: 3.10
Classifier: Programming Language :: Python :: 3.11
Classifier: Programming Language :: Python :: 3.12
Requires-Dist: beautifulsoup4 (>=4.12.3,<5.0.0)
Requires-Dist: html2text (>=2020.1.16,<2021.0.0)
Requires-Dist: requests (>=2.31.0,<3.0.0)
Requires-Dist: tls-client (==1.0.1)
